aioterabox/__init__.py
aioterabox/aiofile_payload.py
aioterabox/api.py
aioterabox/encryption.py
aioterabox/exceptions.py
aioterabox/py.typed
aioterabox-0.1.0.dist-info/licenses/LICENSE
aioterabox-0.1.0.dist-info/METADATA
aioterabox-0.1.0.dist-info/WHEEL
aioterabox-0.1.0.dist-info/top_level.txt
aioterabox-0.1.0.dist-info/RECORD
