Metadata-Version: 2.4
Name: aioterabox
Version: 0.1.0
Summary: Asyncio client for TeraBox cloud storage
Author-email: Ivan Belokobylskiy <belokobylskij@gmail.com>
License-Expression: Apache-2.0
Project-URL: Homepage, https://github.com/devbis/aioterabox
Project-URL: Repository, https://github.com/devbis/aioterabox
Project-URL: Issues, https://github.com/devbis/aioterabox/issues
Keywords: terabox,asyncio,cloud,client
Requires-Python: >=3.10
License-File: LICENSE
Requires-Dist: aiofiles>=22.1.0
Requires-Dist: aiohttp>=3.9
Requires-Dist: cryptography>=3.4
Dynamic: license-file
